random_chat_llm_save_test_package/__init__.py
random_chat_llm_save_test_package-0.2.dist-info/METADATA
random_chat_llm_save_test_package-0.2.dist-info/WHEEL
random_chat_llm_save_test_package-0.2.dist-info/top_level.txt
random_chat_llm_save_test_package-0.2.dist-info/RECORD
