Metadata-Version: 2.4
Name: random_chat_llm_save_test_package
Version: 0.2
Requires-Dist: langchain==0.3.25
Requires-Dist: langchain-community==0.3.25
Requires-Dist: openai==1.97.1
Requires-Dist: pymongo==4.13.2
Dynamic: requires-dist
